kryptor/__init__.py
kryptor/audio_steganography.py
kryptor/blowfish_cipher.py
kryptor/caesar_cipher.py
kryptor/hill_cipher.py
kryptor/img_steganography.py
kryptor/morse.py
kryptor/playfair_cipher.py
kryptor/polybius_cipher.py
kryptor/rail_fence.py
kryptor/vernam_cipher.py
kryptor/vigenere_cipher.py
kryptor-0.5.0.dist-info/LICENSE
kryptor-0.5.0.dist-info/METADATA
kryptor-0.5.0.dist-info/WHEEL
kryptor-0.5.0.dist-info/top_level.txt
kryptor-0.5.0.dist-info/RECORD
