Metadata-Version: 2.1
Name: kryptor
Version: 0.5.0
Summary: Encrypt and Decrypt data with famous cryptography techniques
Author-email: "Het Joshi (DENCODER)" <hetcjoshi1684@gmail.com>
License: GNU GENERAL PUBLIC LICENSE
Project-URL: Homepage, https://github.com/D-ENCODER/KRYPTOR
Project-URL: Bug Tracker, https://github.com/D-ENCODER/KRYPTOR/issues
Classifier: Programming Language :: Python :: 3
Classifier: License :: OSI Approved :: MIT License
Classifier: Operating System :: OS Independent
Requires-Python: >=3.7
License-File: LICENSE
